logstructor/__init__.py
logstructor/config.py
logstructor/context.py
logstructor/exceptions.py
logstructor/formatter.py
logstructor/logger.py
logstructor-0.2.0.dist-info/METADATA
logstructor-0.2.0.dist-info/WHEEL
logstructor-0.2.0.dist-info/licenses/LICENSE
logstructor-0.2.0.dist-info/RECORD
