Metadata-Version: 2.4
Name: logstructor
Version: 0.2.0
Summary: Bringing structure to your logs with simple, Pythonic structured logging
License-File: LICENSE
Requires-Python: >=3.11
